<plugins>

  <plugin name="DD4hepXMLLoader">
    <arg value="file:../DD4hep.trunk/DDExamples/AlignDet/compact/AlephTPC.xml"/>
  </plugin>

  <plugin name="DD4hepVolumeManager"/>
  <plugin name="DD4hepConditionsManagerInstaller"/>

  <plugin name="DD4hepXMLLoader">
    <arg value="file:../DD4hep.trunk/DDExamples/AlignDet/compact/AlephTPC_alignment.xml"/>
  </plugin>
  <plugin name="DD4hepXMLLoader">
    <arg value="file:../DD4hep.trunk/DDExamples/AlignDet/compact/AlephTPC_reset.xml"/>
  </plugin>

  <plugin name="DD4hep_Test_CallbackInstall"/>
  <plugin name="DD4hep_Test_ConditionsAccess"/>
  <plugin name="DD4hep_Test_ConditionsTreeDump"/>
</plugins>
