<lccdd xmlns:compact="http://www.lcsim.org/schemas/compact/1.0" 
       xmlns:xs="http://www.w3.org/2001/XMLSchema" 
       xs:noNamespaceSchemaLocation="http://www.lcsim.org/schemas/compact/1.0/compact.xsd">

  <info name="clic_sid_cdr"
        title="CLIC Silicon Detector CDR"
        author="Christian Grefe"
        url="https://twiki.cern.ch/twiki/bin/view/CLIC/ClicSidCdr"
        status="development"
        version="$Id: compact.xml 1374 2014-11-05 10:49:55Z markus.frank@cern.ch $">
    <comment>The compact format for the CLIC Silicon Detector used for the conceptual design report</comment>        
  </info>

  <includes>
    <gdmlFile  ref="elements.xml"/>
    <gdmlFile  ref="materials.xml"/>
  </includes>
  
  <define>
    <include ref="SiDConstants.xml"/>
  </define>


  <limits>
    <limitset name="cal_limits">
      <limit name="step_length_max" particles="*" value="5.0" unit="mm" />
    </limitset>
    <limitset name="SiTrackerBarrelRegionLimitSet">
      <limit name="step_length_max" particles="*" value="5.0" unit="mm" />
      <limit name="track_length_max" particles="*" value="5.0" unit="mm" />
      <limit name="time_max" particles="*" value="5.0" unit="ns" />
      <limit name="ekin_min" particles="*" value="0.01" unit="MeV" />
      <limit name="range_min" particles="*" value="5.0" unit="mm" />
    </limitset>
  </limits>
  <regions>
    <region name="SiTrackerBarrelRegion" eunit="MeV" lunit="mm" cut="0.001" threshold="0.001">
      <limitsetref name="SiTrackerBarrelRegionLimitSet"/>
    </region>
  </regions>


  <comment>Common Generic visualization attributes</comment>
  <display>
    <vis name="InvisibleNoDaughters"      showDaughters="false" visible="false"/>
    <vis name="InvisibleWithDaughters"    showDaughters="true" visible="false"/>
    <vis name="GreenVis"   alpha="1" r="0.0" g="1.0" b="0.0" showDaughters="true" visible="true"/>
    <vis name="RedVis"     alpha="1" r="1.0" g="0.0" b="0.0" showDaughters="true" visible="true"/>
    <vis name="BlueVis"    alpha="1" r="0.0" g="0.0" b="1.0" showDaughters="true" visible="true"/>
  </display>

  <comment>Additional design specific material definitions</comment>
  <include ref="SiD/SiD_Materials.xml"/>

  <comment>Tracking detectors</comment>
  <include ref="SiD/SiD_Vertex.xml"/>
  <include ref="SiD/SiD_Tracker.xml"/>

  <comment>Calorimeters</comment>
  <include ref="SiD/SiD_Ecal.xml"/>
  <include ref="SiD/SiD_Hcal.xml"/>
  <include ref="SiD/SiD_HcalPlug.xml"/>
  <include ref="SiD/SiD_Muon.xml"/>
  <include ref="SiD/SiD_Lumical.xml"/>
  <include ref="SiD/SiD_Beamcal.xml"/>

  <comment>Beampipe</comment>
  <include ref="SiD/SiD_Beampipe.xml"/>
  
  <comment>Dead material, supports and magnet</comment>
  <include ref="SiD/SiD_Shields.xml"/>
  <include ref="SiD/SiD_Solenoid.xml"/>

  <fields>
    <field name="GlobalSolenoid" type="solenoid" 
	   inner_field="5.0*tesla"
	   outer_field="-1.5*tesla" 
	   zmax="SolenoidCoilOuterZ"
	   outer_radius="SolenoidalFieldRadius">
    </field>
  </fields>
</lccdd>
